{
    "users": [
        {
            "id": 123456,
            "name": "Don Joe",
            "email": "donjoe@mail.com",
            "phone": "098765432",
            "password": "password"
        },
        {
            "id": 64545,
            "name": "Susan Young",
            "email": "sussy@mail.com",
            "phone": "86754323",
            "password": "password1"
        },
        {
            "id": 7424,
            "name": "Don Joe",
            "email": "june@mail.com",
            "phone": "324354623",
            "password": "password2"
        },
        {
            "id": 9788,
            "name": "Don Joe",
            "email": "arya@mail.com",
            "phone": "0986345623",
            "password": "password3"
        },
        {
            "id": 13450,
            "name": "Don Joe",
            "email": "simpleuser@mail.com",
            "phone": "23456876",
            "password": "password4"
        }
    ],
    "transactions": [
        {
            "id": 1234,
            "lender": 123456,
            "borrower": "123456",
            "type": "Lends",
            "amount": 2000,
            "date": "",
            "reason": "Awesome Reason",
            "status": "paid"
        },
        {
            "id": 1235,
            "lender": {
                "id": 123456,
                "name": "Don Joe",
                "email": "donjoe@mail.com",
                "phone": "098765432",
                "password": "password"
            },
            "borrower": {
                "id": 13450,
                "name": "Don Joe",
                "email": "simpleuser@mail.com",
                "phone": "23456876",
                "password": "password4"
            },
            "type": "Lends",
            "amount": 1000,
            "date": "Wed May 04 2022 03:00:00 GMT+0300 (East Africa Time)",
            "reason": "Awesome Reason",
            "status": "paid"
        },
        {
            "id": 1236,
            "lender": {
                "id": 9788,
                "name": "Don Joe",
                "email": "arya@mail.com",
                "phone": "0986345623",
                "password": "password3"
            },
            "borrower": {
                "id": 123456,
                "name": "Don Joe",
                "email": "donjoe@mail.com",
                "phone": "098765432",
                "password": "password"
            },
            "type": "Borrows",
            "amount": 500,
            "date": "Wed May 04 2022 03:00:00 GMT+0300 (East Africa Time)",
            "reason": "Awesome Reason",
            "status": "unpaid"
        }
    ]
}